{"_class":"document","do_objectID":"E11049FC-4FDE-4653-B2DE-79C612224353","colorSpace":0,"currentPageIndex":0,"assets":{"_class":"assetCollection","do_objectID":"67ECAD1B-06D3-4685-A825-70A9958D4622","images":[],"colorAssets":[],"exportPresets":[],"gradientAssets":[],"imageCollection":{"_class":"imageCollection","images":{}},"colors":[],"gradients":[]},"foreignLayerStyles":[],"foreignSymbols":[],"foreignTextStyles":[],"layerStyles":{"_class":"sharedStyleContainer","objects":[]},"layerSymbols":{"_class":"symbolContainer","objects":[]},"layerTextStyles":{"_class":"sharedTextStyleContainer","objects":[]},"pages":[{"_class":"MSJSONFileReference","_ref_class":"MSImmutablePage","_ref":"pages\/48D6F517-D637-4D97-9E95-03D51EF15433"}]}