{"commit":"ebe35af5ba78090fd351ed427ecaafac003e0331","pagesAndArtboards":{"865281BB-184C-413C-BB2B-E215B302216C":{"name":"fill","artboards":{}},"1C91F63E-3934-499E-AFD9-4506F235AE66":{"name":"line","artboards":{}}},"version":121,"fonts":[],"compatibilityVersion":99,"app":"com.bohemiancoding.sketch3","autosaved":0,"variant":"NONAPPSTORE","created":{"commit":"ebe35af5ba78090fd351ed427ecaafac003e0331","appVersion":"59.1","build":86144,"app":"com.bohemiancoding.sketch3","compatibilityVersion":99,"version":121,"variant":"NONAPPSTORE"},"saveHistory":["NONAPPSTORE.86144"],"appVersion":"59.1","build":86144}